AUTHORS.rst
CONTRIBUTING.rst
HISTORY.rst
LICENSE
MANIFEST.in
README.rst
setup.cfg
setup.py
docs/Makefile
docs/authors.rst
docs/conf.py
docs/contributing.rst
docs/history.rst
docs/index.rst
docs/installation.rst
docs/make.bat
docs/readme.rst
docs/selenium_extensions.rst
docs/usage.rst
docs/_build/html/_static/ajax-loader.gif
docs/_build/html/_static/comment-bright.png
docs/_build/html/_static/comment-close.png
docs/_build/html/_static/comment.png
docs/_build/html/_static/down-pressed.png
docs/_build/html/_static/down.png
docs/_build/html/_static/file.png
docs/_build/html/_static/minus.png
docs/_build/html/_static/plus.png
docs/_build/html/_static/up-pressed.png
docs/_build/html/_static/up.png
requirements/dev.txt
requirements/prod.txt
selenium_extensions/__init__.py
selenium_extensions/core.py
selenium_extensions/drivers.py
selenium_extensions/exceptions.py
selenium_extensions/helpers.py
selenium_extensions.egg-info/PKG-INFO
selenium_extensions.egg-info/SOURCES.txt
selenium_extensions.egg-info/dependency_links.txt
selenium_extensions.egg-info/not-zip-safe
selenium_extensions.egg-info/requires.txt
selenium_extensions.egg-info/top_level.txt