Metadata-Version: 1.1
Name: selenium-extensions
Version: 0.1.2
Summary: Tools that will make writing tests, bots and scrapers using Selenium much easier
Home-page: https://github.com/pythad/selenium_extensions
Author: Vladyslav Ovchynnykov
Author-email: ovd4mail@gmail.com
License: MIT license
Keywords: selenium_extensions
Platform: UNKNOWN
Classifier: Development Status :: 5 - Production/Stable
Classifier: Intended Audience :: Developers
Classifier: License :: OSI Approved :: MIT License
Classifier: Natural Language :: English
Classifier: Programming Language :: Python :: 3
Classifier: Programming Language :: Python :: 3.3
Classifier: Programming Language :: Python :: 3.4
Classifier: Programming Language :: Python :: 3.5
